{"dumper": "to_cloudpickle", "time": [2024, 2, 9, 20, 5, 38, 4, 40, -1], "conda_list": "# packages in environment at /gpfs/soma_fs/scratch/meulemeester/anaconda_isf3.8:\n#\n# Name                    Version                   Build  Channel\n_ipyw_jlab_nb_ext_conf    0.1.0                    py38_0  \n_libgcc_mutex             0.1                        main  \nalabaster                 0.7.12                     py_0  \nanaconda                  2020.11                  py38_0  \nanaconda-client           1.7.2                    py38_0  \nanaconda-navigator        1.10.0                   py38_0  \nanaconda-project          0.8.4                      py_0  \nannotated-types           0.5.0                    pypi_0    pypi\naplus                     0.11.0                   pypi_0    pypi\nargh                      0.26.2                   py38_0  \nargon2-cffi               20.1.0           py38h7b6447c_1  \nasn1crypto                1.4.0                      py_0  \nastroid                   2.4.2                    py38_0  \nastropy                   4.0.2            py38h7b6447c_0  \nasttokens                 2.4.1                    pypi_0    pypi\nasync_generator           1.10                       py_0  \natomicwrites              1.4.0                      py_0  \nattrs                     20.3.0             pyhd3eb1b0_0  \nautopep8                  1.5.4                      py_0  \nbabel                     2.13.0                   pypi_0    pypi\nbackcall                  0.2.0                      py_0  \nbackports                 1.0                        py_2  \nbackports.functools_lru_cache 1.6.1                      py_0  \nbackports.shutil_get_terminal_size 1.0.0                    py38_2  \nbackports.tempfile        1.0                        py_1  \nbackports.weakref         1.0.post1                  py_1  \nbeautifulsoup4            4.9.3              pyhb0f4dca_0  \nbitarray                  1.6.1            py38h27cfd23_0  \nbkcharts                  0.2                      py38_0  \nblake3                    0.3.3                    pypi_0    pypi\nblas                      1.0                         mkl  \nbleach                    3.2.1                      py_0  \nblosc                     1.10.2                   pypi_0    pypi\nbluepyopt                 1.9.126                  pypi_0    pypi\nbokeh                     2.2.3                    py38_0  \nboto                      2.49.0                   py38_0  \nbottleneck                1.3.2            py38heb32a55_1  \nbrotlipy                  0.7.0           py38h7b6447c_1000  \nbzip2                     1.0.8                h7b6447c_0  \nca-certificates           2020.10.14                    0  \ncairo                     1.14.12              h8948797_3  \ncertifi                   2020.6.20          pyhd3eb1b0_3  \ncffi                      1.14.3           py38he30daa8_0  \nchardet                   3.0.4                 py38_1003  \ncharset-normalizer        3.3.0                    pypi_0    pypi\nchart-studio              1.1.0                    pypi_0    pypi\nclick                     7.1.2                      py_0  \ncloudpickle               1.6.0                      py_0  \nclyent                    1.2.2                    py38_1  \ncolorama                  0.4.4                      py_0  \ncomm                      0.2.1                    pypi_0    pypi\nconda                     4.9.2            py38h06a4308_0  \nconda-build               3.20.5                   py38_1  \nconda-env                 2.6.0                         1  \nconda-package-handling    1.7.2            py38h03888b9_0  \nconda-verify              3.4.2                      py_1  \ncontextlib2               0.6.0.post1                py_0  \ncoverage                  7.3.0                    pypi_0    pypi\ncryptography              3.1.1            py38h1ba5d50_0  \ncurl                      7.71.1               hbc83047_1  \ncycler                    0.10.0                   py38_0  \ncython                    0.29.21          py38he6710b0_0  \ncytoolz                   0.11.0           py38h7b6447c_0  \ndash                      2.9.3                    pypi_0    pypi\ndash-core-components      2.0.0                    pypi_0    pypi\ndash-html-components      2.0.0                    pypi_0    pypi\ndash-table                5.0.0                    pypi_0    pypi\ndask                      2.30.0                     py_0  \ndask-core                 2.30.0                     py_0  \ndask-glm                  0.3.0                    pypi_0    pypi\ndask-ml                   2023.3.24                pypi_0    pypi\ndbus                      1.13.18              hb2f20db_0  \ndeap                      1.3.1                    pypi_0    pypi\ndebugpy                   1.8.0                    pypi_0    pypi\ndecorator                 4.4.2                      py_0  \ndefusedxml                0.6.0                      py_0  \ndiff-match-patch          20200713                   py_0  \ndistributed               2.30.1           py38h06a4308_0  \ndocutils                  0.20.1                   pypi_0    pypi\nefel                      3.1.70                   pypi_0    pypi\nentrypoints               0.3                      py38_0  \net_xmlfile                1.0.1                   py_1001  \nexceptiongroup            1.1.2                    pypi_0    pypi\nexecnet                   2.0.2                    pypi_0    pypi\nexecuting                 2.0.1                    pypi_0    pypi\nexpat                     2.2.10               he6710b0_2  \nfastcache                 1.1.0            py38h7b6447c_0  \nfasteners                 0.16                     pypi_0    pypi\nfastjsonschema            2.15.3                   pypi_0    pypi\nfilelock                  3.0.12                     py_0  \nflake8                    3.8.4                      py_0  \nflask                     1.1.2                      py_0  \nflask-cors                4.0.0                    pypi_0    pypi\nfontconfig                2.13.0               h9420a91_0  \nfreetype                  2.10.4               h5ab3b9f_0  \nfribidi                   1.0.10               h7b6447c_0  \nfrozendict                2.3.8                    pypi_0    pypi\nfsspec                    0.8.3                      py_0  \nfuro                      2023.9.10                pypi_0    pypi\nfuture                    0.18.2                   py38_1  \nget_terminal_size         1.0.0                haa9412d_0  \ngevent                    20.9.0           py38h7b6447c_0  \nglib                      2.66.1               h92f7085_0  \nglob2                     0.7                        py_0  \ngmp                       6.1.2                h6c8ec71_1  \ngmpy2                     2.0.8            py38hd5f6e3b_3  \ngraphite2                 1.3.14               h23475e2_0  \ngreenlet                  0.4.17           py38h7b6447c_0  \ngst-plugins-base          1.14.0               hbbd80ab_1  \ngstreamer                 1.14.0               hb31296c_0  \nh5py                      2.10.0           py38h7918eee_0  \nharfbuzz                  2.4.0                hca77d97_1  \nhdf5                      1.10.4               hb1b8bf9_0  \nheapdict                  1.0.1                      py_0  \nhtml5lib                  1.1                        py_0  \nicu                       58.2                 he6710b0_3  \nidna                      2.10                       py_0  \nimageio                   2.9.0                      py_0  \nimagesize                 1.4.1                    pypi_0    pypi\nimportlib-metadata        4.11.3                   pypi_0    pypi\nimportlib-resources       5.13.0                   pypi_0    pypi\nimportlib_metadata        2.0.0                         1  \ninflection                0.5.1                    pypi_0    pypi\niniconfig                 1.1.1                      py_0  \nintel-openmp              2020.2                      254  \nintervaltree              3.1.0                      py_0  \nipykernel                 6.29.0                   pypi_0    pypi\nipython                   8.12.3                   pypi_0    pypi\nipython_genutils          0.2.0                    py38_0  \nipywidgets                7.5.1                      py_1  \nisort                     5.6.4                      py_0  \nitsdangerous              1.1.0                      py_0  \njbig                      2.1                  hdba287a_0  \njdcal                     1.4.1                      py_0  \njedi                      0.17.1                   py38_0  \njeepney                   0.5.0              pyhd3eb1b0_0  \njinja2                    3.0.3                    pypi_0    pypi\njoblib                    1.3.2                    pypi_0    pypi\njpeg                      9b                   h024ee3a_2  \njson5                     0.9.5                      py_0  \njsonschema                3.2.0                      py_2  \njupyter                   1.0.0                    py38_7  \njupyter-client            8.6.0                    pypi_0    pypi\njupyter-core              5.7.1                    pypi_0    pypi\njupyter_console           6.2.0                      py_0  \njupyterlab                2.2.6                      py_0  \njupyterlab_pygments       0.1.2                      py_0  \njupyterlab_server         1.2.0                      py_0  \nkazoo                     2.8.0                    pypi_0    pypi\nkeyring                   21.4.0                   py38_1  \nkiwisolver                1.3.0            py38h2531618_0  \nkrb5                      1.18.2               h173b8e3_0  \nlazy-object-proxy         1.4.3            py38h7b6447c_0  \nlcms2                     2.11                 h396b838_0  \nld_impl_linux-64          2.33.1               h53a641e_7  \nlibarchive                3.4.2                h62408e4_0  \nlibcurl                   7.71.1               h20c2e04_1  \nlibedit                   3.1.20191231         h14c3975_1  \nlibffi                    3.3                  he6710b0_2  \nlibgcc-ng                 9.1.0                hdf63c60_0  \nlibgfortran-ng            7.3.0                hdf63c60_0  \nliblief                   0.10.1               he6710b0_0  \nlibllvm10                 10.0.1               hbcb73fb_5  \nlibpng                    1.6.37               hbc83047_0  \nlibsodium                 1.0.18               h7b6447c_0  \nlibspatialindex           1.9.3                he6710b0_0  \nlibssh2                   1.9.0                h1ba5d50_1  \nlibstdcxx-ng              9.1.0                hdf63c60_0  \nlibtiff                   4.1.0                h2733197_1  \nlibtool                   2.4.6             h7b6447c_1005  \nlibuuid                   1.0.3                h1bed415_2  \nlibxcb                    1.14                 h7b6447c_0  \nlibxml2                   2.9.10               hb55368b_3  \nlibxslt                   1.1.34               hc22bd24_0  \nllvmlite                  0.34.0           py38h269e1b5_4  \nlocket                    0.2.0                    py38_1  \nlxml                      4.6.1            py38hefd8a0e_0  \nlz4-c                     1.9.2                heb0550a_3  \nlzo                       2.10                 h7b6447c_2  \nmarkdown-it-py            3.0.0                    pypi_0    pypi\nmarkupsafe                2.1.3                    pypi_0    pypi\nmatplotlib                3.3.2                         0  \nmatplotlib-base           3.3.2            py38h817c723_0  \nmatplotlib-inline         0.1.6                    pypi_0    pypi\nmccabe                    0.6.1                    py38_1  \nmdurl                     0.1.2                    pypi_0    pypi\nmistune                   0.8.4           py38h7b6447c_1000  \nmkl                       2020.2                      256  \nmkl-service               2.3.0            py38he904b0f_0  \nmkl_fft                   1.2.0            py38h23d657b_0  \nmkl_random                1.1.1            py38h0573a6f_0  \nmock                      4.0.2                      py_0  \nmodulegraph2              2.2.1                    pypi_0    pypi\nmore-itertools            8.6.0              pyhd3eb1b0_0  \nmpc                       1.1.0                h10f8cd9_1  \nmpfr                      4.0.2                hb69a4c5_1  \nmpmath                    1.1.0                    py38_0  \nmsgpack-python            1.0.0            py38hfd86e86_1  \nmultipledispatch          0.6.0                    py38_0  \nnavigator-updater         0.2.1                    py38_0  \nnbclient                  0.5.1                      py_0  \nnbconvert                 6.0.7                    py38_0  \nnbformat                  5.0.8                      py_0  \nncurses                   6.2                  he6710b0_1  \nneo                       0.9.0                    pypi_0    pypi\nnest-asyncio              1.4.2              pyhd3eb1b0_0  \nnetworkx                  2.5                        py_0  \nneuron                    7.8.2                    pypi_0    pypi\nnltk                      3.5                        py_0  \nnose                      1.3.7                    py38_2  \nnotebook                  6.1.4                    py38_0  \nnumba                     0.51.2           py38h0573a6f_1  \nnumexpr                   2.7.1            py38h423224d_0  \nnumpy                     1.19.2                   pypi_0    pypi\nnumpydoc                  1.1.0              pyhd3eb1b0_1  \nobjectgraph               1.0.3                    pypi_0    pypi\nolefile                   0.46                       py_0  \nopenpyxl                  3.0.5                      py_0  \nopenssl                   1.1.1h               h7b6447c_0  \npackaging                 23.2                     pypi_0    pypi\npandas                    1.1.3            py38he6710b0_0  \npandas-msgpack            0.1.4+14.gfcb0471.dirty          pypi_0    pypi\npandoc                    2.11                 hb0f4dca_0  \npandocfilters             1.4.3            py38h06a4308_1  \npango                     1.45.3               hd140c19_0  \nparameters                0.2.1                    pypi_0    pypi\nparso                     0.7.0                      py_0  \npartd                     1.1.0                      py_0  \npatchelf                  0.12                 he6710b0_0  \npath                      15.0.0                   py38_0  \npath.py                   12.5.0                        0  \npathlib2                  2.3.5                    py38_0  \npathtools                 0.1.2                      py_1  \npatsy                     0.5.1                    py38_0  \npcre                      8.44                 he6710b0_0  \npep8                      1.7.1                    py38_0  \npexpect                   4.8.0                    py38_0  \npickleshare               0.7.5                 py38_1000  \npillow                    8.2.0                    pypi_0    pypi\npip                       20.2.4           py38h06a4308_0  \npixman                    0.40.0               h7b6447c_0  \npkginfo                   1.6.1            py38h06a4308_0  \nplatformdirs              3.11.0                   pypi_0    pypi\nplotly                    5.17.0                   pypi_0    pypi\npluggy                    0.13.1                   py38_0  \nply                       3.11                     py38_0  \npooch                     1.8.0                    pypi_0    pypi\nprogressbar2              4.2.0                    pypi_0    pypi\nprometheus_client         0.8.0                      py_0  \nprompt-toolkit            3.0.43                   pypi_0    pypi\nprompt_toolkit            3.0.8                         0  \npsutil                    5.7.2            py38h7b6447c_0  \nptyprocess                0.6.0                    py38_0  \npure-eval                 0.2.2                    pypi_0    pypi\npy                        1.9.0                      py_0  \npy-lief                   0.10.1           py38h403a769_0  \npyarrow                   12.0.1                   pypi_0    pypi\npycodestyle               2.6.0                      py_0  \npycosat                   0.6.3            py38h7b6447c_1  \npycparser                 2.20                       py_2  \npycurl                    7.43.0.6         py38h1ba5d50_0  \npydantic                  1.10.4                   pypi_0    pypi\npydeps                    1.12.17                  pypi_0    pypi\npydocstyle                5.1.1                      py_0  \npyflakes                  2.2.0                      py_0  \npygments                  2.16.1                   pypi_0    pypi\npylint                    2.6.0                    py38_0  \npyodbc                    4.0.30           py38he6710b0_0  \npyopenssl                 19.1.0                     py_1  \npyparsing                 2.4.7                      py_0  \npypdf2                    1.26.0                   pypi_0    pypi\npyqt                      5.9.2            py38h05f1152_4  \npyrsistent                0.17.3           py38h7b6447c_0  \npysocks                   1.7.1                    py38_0  \npytables                  3.6.1            py38h9fd0a39_0  \npytest                    7.4.0                    pypi_0    pypi\npytest-cov                4.1.0                    pypi_0    pypi\npytest-xdist              3.3.1                    pypi_0    pypi\npython                    3.8.5                h7579374_1  \npython-dateutil           2.8.2                    pypi_0    pypi\npython-graphviz           0.20.1                   pypi_0    pypi\npython-jsonrpc-server     0.4.0                      py_0  \npython-language-server    0.35.1                     py_0  \npython-libarchive-c       2.9                        py_0  \npython-utils              3.7.0                    pypi_0    pypi\npytz                      2020.1                     py_0  \npyvista                   0.42.3                   pypi_0    pypi\npywavelets                1.1.1            py38h7b6447c_2  \npyxdg                     0.27               pyhd3eb1b0_0  \npyyaml                    5.3.1            py38h7b6447c_1  \npyzmq                     25.1.2                   pypi_0    pypi\nqdarkstyle                2.8.1                      py_0  \nqt                        5.9.7                h5867ecd_1  \nqtawesome                 1.0.1                      py_0  \nqtconsole                 4.7.7                      py_0  \nqtpy                      1.9.0                      py_0  \nquantities                0.12.4                   pypi_0    pypi\nreadline                  8.0                  h7b6447c_0  \nredis                     3.5.3                    pypi_0    pypi\nregex                     2020.10.15       py38h7b6447c_0  \nrequests                  2.31.0                   pypi_0    pypi\nretrying                  1.3.3                    pypi_0    pypi\nrich                      13.5.2                   pypi_0    pypi\nripgrep                   12.1.1                        0  \nrope                      0.18.0                     py_0  \nrtree                     0.9.4                    py38_1  \nruamel_yaml               0.15.87          py38h7b6447c_1  \nscandir                   1.10.0                   pypi_0    pypi\nscikit-image              0.17.2           py38hdf5156a_0  \nscikit-learn              1.3.2                    pypi_0    pypi\nscipy                     1.5.2            py38h0b6359f_0  \nscooby                    0.9.2                    pypi_0    pypi\nseaborn                   0.11.0                     py_0  \nsecretstorage             3.1.2                    py38_0  \nsend2trash                1.5.0                    py38_0  \nsetuptools                50.3.1           py38h06a4308_1  \nsimplegeneric             0.8.1                    py38_2  \nsimpleitk                 2.0.2                    pypi_0    pypi\nsingledispatch            3.4.0.3                 py_1001  \nsip                       4.19.13          py38he6710b0_0  \nsix                       1.15.0           py38h06a4308_0  \nsnowballstemmer           2.0.0                      py_0  \nsortedcollections         1.2.1                      py_0  \nsortedcontainers          2.2.2                      py_0  \nsoupsieve                 2.0.1                      py_0  \nsparse                    0.14.0                   pypi_0    pypi\nsphinx                    7.1.2                    pypi_0    pypi\nsphinx-basic-ng           1.0.0b2                  pypi_0    pypi\nsphinx-paramlinks         0.6.0                    pypi_0    pypi\nsphinxcontrib             1.0                      py38_1  \nsphinxcontrib-applehelp   1.0.2                      py_0  \nsphinxcontrib-devhelp     1.0.2                      py_0  \nsphinxcontrib-htmlhelp    2.0.1                    pypi_0    pypi\nsphinxcontrib-jsmath      1.0.1                      py_0  \nsphinxcontrib-qthelp      1.0.3                      py_0  \nsphinxcontrib-serializinghtml 1.1.5                    pypi_0    pypi\nsphinxcontrib-websupport  1.2.4                      py_0  \nspyder                    4.1.5                    py38_0  \nspyder-kernels            1.9.4                    py38_0  \nsqlalchemy                1.3.20           py38h7b6447c_0  \nsqlite                    3.33.0               h62c20be_0  \nstack-data                0.6.3                    pypi_0    pypi\nstatsmodels               0.12.0           py38h7b6447c_0  \nstdlib-list               0.10.0                   pypi_0    pypi\nsumatra                   0.7.4                    pypi_0    pypi\nsympy                     1.6.2            py38h06a4308_1  \ntabulate                  0.9.0                    pypi_0    pypi\ntbb                       2020.3               hfd86e86_0  \ntblib                     1.7.0                      py_0  \ntenacity                  8.2.3                    pypi_0    pypi\nterminado                 0.9.1                    py38_0  \ntestpath                  0.4.4                      py_0  \nthreadpoolctl             2.1.0              pyh5ca1d4c_0  \ntifffile                  2020.10.1        py38hdd07704_2  \ntk                        8.6.10               hbc83047_0  \ntoml                      0.10.1                     py_0  \ntoolz                     0.11.1                     py_0  \ntorch                     1.8.1                    pypi_0    pypi\ntorchaudio                0.8.1                    pypi_0    pypi\ntorchvision               0.9.1                    pypi_0    pypi\ntornado                   6.4                      pypi_0    pypi\ntqdm                      4.50.2                     py_0  \ntraitlets                 5.14.1                   pypi_0    pypi\ntyping-extensions         4.7.1                    pypi_0    pypi\nujson                     4.0.1            py38he6710b0_0  \nunicodecsv                0.14.1                   py38_0  \nunixodbc                  2.3.9                h7b6447c_0  \nurllib3                   1.25.11                    py_0  \nvaex                      4.16.0                   pypi_0    pypi\nvaex-astro                0.9.3                    pypi_0    pypi\nvaex-core                 4.16.1                   pypi_0    pypi\nvaex-hdf5                 0.14.1                   pypi_0    pypi\nvaex-jupyter              0.8.2                    pypi_0    pypi\nvaex-ml                   0.18.3                   pypi_0    pypi\nvaex-server               0.8.1                    pypi_0    pypi\nvaex-viz                  0.5.4                    pypi_0    pypi\nvtk                       9.2.6                    pypi_0    pypi\nwatchdog                  0.10.3                   py38_0  \nwcwidth                   0.2.5                      py_0  \nwebencodings              0.5.1                    py38_1  \nwerkzeug                  1.0.1                      py_0  \nwheel                     0.35.1                     py_0  \nwidgetsnbextension        3.5.1                    py38_0  \nwrapt                     1.11.2           py38h7b6447c_0  \nwurlitzer                 2.0.1                    py38_0  \nxlrd                      1.2.0                      py_0  \nxlsxwriter                1.3.7                      py_0  \nxlwt                      1.3.0                    py38_0  \nxmltodict                 0.12.0                     py_0  \nxz                        5.2.5                h7b6447c_0  \nyaml                      0.2.5                h7b6447c_0  \nyapf                      0.30.0                     py_0  \nzeromq                    4.3.3                he6710b0_3  \nzict                      2.0.0                      py_0  \nzipp                      3.4.0              pyhd3eb1b0_0  \nzlib                      1.2.11               h7b6447c_3  \nzope                      1.0                      py38_1  \nzope.event                4.5.0                    py38_0  \nzope.interface            5.1.2            py38h7b6447c_0  \nzstd                      1.4.5                h9ceee32_0  \n", "module_versions": {"re": "2.2.1", "json": "2.0.9", "platform": "1.0.8", "_ctypes": "1.1.0", "ctypes": "1.1.0", "zmq": "25.1.2", "logging": "0.5.1.2", "traitlets": "5.14.1", "jupyter_core": "5.7.1", "zlib": "1.0", "colorama": "0.4.4", "_curses": "b'2.2'", "socketserver": "0.4", "argparse": "1.1", "dateutil": "2.8.2", "six": "1.15.0", "_decimal": "1.70", "decimal": "1.70", "platformdirs": "3.11.0", "_csv": "1.0", "csv": "1.0", "jupyter_client": "8.6.0", "ipykernel": "6.29.0", "executing": "2.0.1", "pure_eval": "0.2.2", "stack_data": "0.6.3", "pygments": "2.16.1", "ptyprocess": "0.6.0", "pexpect": "4.8.0", "pickleshare": "0.7.5", "backcall": "0.2.0", "decorator": "4.4.2", "wcwidth": "0.2.5", "prompt_toolkit": "3.0.43", "parso": "0.7.0", "jedi": "0.17.1", "IPython": "8.12.3", "comm": "0.2.1", "psutil": "5.7.2", "debugpy": "1.8.0", "pydevd": "2.9.5", "packaging": "23.2", "ipython_genutils": "0.2.0", "ipywidgets": "7.5.1", "distutils": "3.8.5", "numpy": "1.19.2", "pyparsing": "2.4.7", "cycler": "0.10.0", "kiwisolver": "1.3.0", "matplotlib": "3.3.2", "PIL": "8.2.0", "cffi": "1.14.3", "matplotlib_inline": "0.1.6", "Interface": "heads/publish+0.gc1986661.dirty", "pytz": "2020.1", "bottleneck": "1.3.2", "pandas": "1.1.3", "yaml": "5.3.1", "toolz": "0.11.1", "cytoolz": "0.11.0", "tlz": "0.11.0", "cloudpickle": "1.6.0", "tblib": "1.7.0", "dask": "2.30.0", "llvmlite": "0.34.0", "scipy": "1.5.2", "numba": "0.51.2", "sparse": "0.14.0", "numexpr": "2.7.1", "pyarrow": "12.0.1", "fsspec": "0.8.3", "click": "7.1.2", "blosc": "1.10.2", "sortedcontainers": "2.2.2", "distributed": "2.30.1", "statsmodels": "0.12.0", "seaborn": "0.11.0", "kazoo": "2.8.0", "tables": "3.6.1", "neuron": "7.8.2", "sumatra": "0.7.4", "future": "0.18.2", "parameters": "0.2.1", "joblib": "1.3.2", "threadpoolctl": "2.1.0", "sklearn": "1.3.2", "pandas_msgpack": "0.1.4+14.gfcb0471.dirty", "scandir": "1.10.0", "markupsafe": "2.1.3", "jinja2": "3.0.3", "werkzeug": "1.0.1", "itsdangerous": "1.1.0", "greenlet": "0.4.17", "flask": "1.1.2", "dash": "2.9.3", "plotly": "5.17.0", "deap": "1.3", "past": "0.18.2", "bluepyopt": "1.9.126", "filelock": "3.0.12", "blake3": "0.3.3", "ipaddress": "1.0", "pydantic": "1.10.4", "attr": "20.3.0", "gevent": "20.9.0", "tabulate": "0.9.0", "frozendict": "2.3.8", "vaex": {"vaex": "4.16.0", "vaex-core": "4.16.1", "vaex-viz": "0.5.4", "vaex-hdf5": "0.14.1", "vaex-server": "0.8.1", "vaex-astro": "0.9.3", "vaex-jupyter": "0.8.2", "vaex-ml": "0.18.3"}, "flask_cors": "4.0.0"}, "history": "%matplotlib inline\nimport Interface as I\nfrom getting_started import getting_started_dir\ndb_path = I.os.path.join(getting_started_dir, 'example_simulation_data', 'biophysics')\ndb = I.DataBase(db_path)\n# init\nobjectives_2BAC = [\n       '1BAC_APheight', '1BAC_ISI', '1BAC_ahpdepth', '1BAC_caSpike_height', \n       '1BAC_caSpike_width', '1BAC_spikecount', '2BAC_APheight', '2BAC_ISI', \n       '2BAC_ahpdepth', '2BAC_caSpike_height', '2BAC_caSpike_width', '2BAC_spikecount',\n        'bAP_APheight', 'bAP_APwidth', 'bAP_att2', 'bAP_att3', 'bAP_spikecount']\nparams_py3 = [\n       'ephys.CaDynamics_E2_v2.apic.decay',\n       'ephys.CaDynamics_E2_v2.apic.gamma',\n       'ephys.CaDynamics_E2_v2.axon.decay',\n       'ephys.CaDynamics_E2_v2.axon.gamma',\n       'ephys.CaDynamics_E2_v2.soma.decay',\n       'ephys.CaDynamics_E2_v2.soma.gamma',\n       'ephys.Ca_HVA.apic.gCa_HVAbar',\n       'ephys.Ca_HVA.axon.gCa_HVAbar',\n       'ephys.Ca_HVA.soma.gCa_HVAbar',\n       'ephys.Ca_LVAst.apic.gCa_LVAstbar',\n       'ephys.Ca_LVAst.axon.gCa_LVAstbar',\n       'ephys.Ca_LVAst.soma.gCa_LVAstbar',\n       'ephys.Im.apic.gImbar',\n       'ephys.K_Pst.axon.gK_Pstbar',\n       'ephys.K_Pst.soma.gK_Pstbar',\n       'ephys.K_Tst.axon.gK_Tstbar',\n       'ephys.K_Tst.soma.gK_Tstbar',\n       'ephys.NaTa_t.apic.gNaTa_tbar',\n       'ephys.NaTa_t.axon.gNaTa_tbar',\n       'ephys.NaTa_t.soma.gNaTa_tbar',\n       'ephys.Nap_Et2.axon.gNap_Et2bar',\n       'ephys.Nap_Et2.soma.gNap_Et2bar',\n       'ephys.SK_E2.apic.gSK_E2bar',\n       'ephys.SK_E2.axon.gSK_E2bar',\n       'ephys.SK_E2.soma.gSK_E2bar',\n       'ephys.SKv3_1.apic.gSKv3_1bar',\n       'ephys.SKv3_1.apic.offset',\n       'ephys.SKv3_1.apic.slope',\n       'ephys.SKv3_1.axon.gSKv3_1bar',\n       'ephys.SKv3_1.soma.gSKv3_1bar',\n       'ephys.none.apic.g_pas',\n       'ephys.none.axon.g_pas',\n       'ephys.none.dend.g_pas',\n       'ephys.none.soma.g_pas',\n       'scale_apical.scale']\n# get the biophysical parameters of one examplary biophysical model\np = db['example_models'].iloc[0][params_py3]\np\nfixed_params = {\n 'bAP.hay_measure.recSite1': 294.8203371921156,\n 'bAP.hay_measure.recSite2': 474.8203371921156,\n 'hot_zone.min_': 384.8203371921156,\n 'hot_zone.max_': 584.8203371921156,\n 'hot_zone.outsidescale_sections': [\n     23,24,25,26,27,28,29,31,32,33,35,37,38,40,42,43,44,46,48,50,51,5254,56,58,60],\n 'morphology.filename': '/gpfs/soma_fs/scratch/abast/results/20220325_run_low_refractory_period_optimization3_two_BAC_plus_step/89_r7dr3xz7_/mdb/morphology_le6tfw7c_/89_L5_CDK20050712_nr6L5B_dend_PC_neuron_transform_registered_C2.hoc'}\n# def import_Interface():\n#     import Interface\nfrom biophysics_fitting.hay_complete_default_setup_python import get_Simulator\nfrom biophysics_fitting.L5tt_parameter_setup import get_L5tt_template_v2\ns = get_Simulator(fixed_params)\n# s.setup.check_funs.append(import_Interface)            \ns.setup.cell_param_generator = get_L5tt_template_v2\ncell, _ = s.get_simulated_cell(p, 'bAP')\n%matplotlib inline\nI.plt.plot(cell.tVec, cell.sections[0].recVList[0])\ndb['89']['get_fixed_params'](db['89'])\ndb['89']['get_fixed_params'](db['89'])\nfixed_params = db['89']['get_fixed_params'](db['89'])\nfixed_params = db['89']['get_fixed_params'](db['89'])\nfixed_params\nfixed_params = db['89']['get_fixed_params'](db['89'])\nfixed_params\nfrom biophysics_fitting.hay_complete_default_setup_python import get_Simulator\nfrom biophysics_fitting.L5tt_parameter_setup import get_L5tt_template_v2\ns = get_Simulator(fixed_params)\ns.setup.cell_param_generator = get_L5tt_template_v2\n# Where exactly do we inject the epsp? We already saved this information:\n# Morphology \"89\" has a rather deep bifurcation\n# epsp injection at 294um from the soma.\ndb['89']['get_fixed_params'](db, '89')['BAC.stim.dist']\n# Where exactly do we inject the epsp? We already saved this information:\n# Morphology \"89\" has a rather deep bifurcation\n# epsp injection at 294um from the soma.\ndb['89']['get_fixed_params']('89')['BAC.stim.dist']\n# Where exactly do we inject the epsp? We already saved this information:\n# Morphology \"89\" has a rather deep bifurcation\n# epsp injection at 294um from the soma.\ndb['89']['get_fixed_params'](db['89'], '89')['BAC.stim.dist']\n# Where exactly do we inject the epsp? We already saved this information:\n# Morphology \"89\" has a rather deep bifurcation\n# epsp injection at 294um from the soma.\ndb['89']['get_fixed_params'](db['89'])['BAC.stim.dist']\ndef get_fixed_params(db, key):\n    p = db[key]['get_fixed_params'](db[key])\n    return p\n\ndef get_simulator(db, key):\n    s = db[key]['get_Simulator'](db[key])\n    return s\nfixed_params = get_fixed_params(db, '89')\nfixed_params\nfrom biophysics_fitting.hay_complete_default_setup_python import get_Simulator\nfrom biophysics_fitting.L5tt_parameter_setup import get_L5tt_template_v2\ns = get_Simulator(fixed_params)\ns.setup.cell_param_generator = get_L5tt_template_v2\n# Where exactly do we inject the epsp? We already saved this information:\n# Morphology \"89\" has a rather deep bifurcation\n# epsp injection at 294um from the soma.\nfixed_params['BAC.stim.dist']\nfixed_params['BAC.stim.dist']\nfixed_params['BAC.stim.dist']\nsetup_apical_epsp_injection(\n    cell, \n    dist = get_fixed_params(db, '89')['BAC.stim.dist'],\n    amplitude=0.5,  # [nA]\n    delay=300,  # [ms]\n    rise=1.0,  # [ms]\n    decay=5  # [ms]\n    )\nfrom biophysics_fitting.setup_stim import setup_apical_epsp_injection\nsetup_apical_epsp_injection(\n    cell, \n    dist = get_fixed_params(db, '89')['BAC.stim.dist'],\n    amplitude=0.5,  # [nA]\n    delay=300,  # [ms]\n    rise=1.0,  # [ms]\n    decay=5  # [ms]\n    )\ns.get_simulated_cell(p, 'BAC')\ncell, p = s.get_simulated_cell(p, 'BAC')\n%matplotlib inline\nI.plt.plot(cell.tVec, cell.sections[0].recVList[0])\ndb['example_models'].iloc[0]\ndb['example_models'].iloc[0]['morphology.filename']\ndb['example_models']\ndb['example_models']['morphology.filename']\ndb['example_models']['morphology.filename'].values\ndb['morphology']\ndb['89['morphology']\ndb['89']['morphology']\ndf = db['example_models']\ndf['morphology.filename']\ndf['morphology.filename'].values\ndf['morphology.filename'] = [\n    I.os.path.join(\n        getting_started_dir, 'anatomical_constraints',\n        '89_L5_CDK20050712_nr6L5B_dend_PC_neuron_transform_registered_C2.hoc'\n    )\n]*len(df)\ndf['morphology.filename'] = [\n        '89_L5_CDK20050712_nr6L5B_dend_PC_neuron_transform_registered_C2.hoc'\n]*len(df)\ndb['morphology']\ndb['89['morphology']\ndb['89']['morphology']\ndb['89']['morphology'] = '89_L5_CDK20050712_nr6L5B_dend_PC_neuron_transform_registered_C2.hoc'\n%matplotlib inline\nimport Interface as I\nfrom getting_started import getting_started_dir\ndb_path = I.os.path.join(getting_started_dir, 'example_simulation_data', 'biophysics')\ndb = I.DataBase(db_path)\n# db['89']['morphology'] = I.os.path.join(\n#     getting_started_dir, 'anatomical_constraints', db['89']['morphology']\n# )\ndb['morphology']\ndb['89']['morphology']\ndb['example_models']\ndb['example_models']['morphology']\ndb['example_models']['morphology.filename']\ndb['example_models']['morphology.filename'] = [\n    '89_L5_CDK20050712_nr6L5B_dend_PC_neuron_transform_registered_C2.hoc'\n]*len(df)\ndb['example_models']['morphology.filename']\ndf = db['example_models']['morphology.filename']\ndf['example_models']['morphology.filename']= [\n    '89_L5_CDK20050712_nr6L5B_dend_PC_neuron_transform_registered_C2.hoc'\n]*len(df)\ndf = db['example_models']\ndf['morphology.filename']= [\n    '89_L5_CDK20050712_nr6L5B_dend_PC_neuron_transform_registered_C2.hoc'\n]*len(df)\ndb['example_models'] = df", "hostname": "somacpu081\n", "metadata_creation_time": "together_with_new_key", "version": "heads/publish+0.gc1986661.dirty", "full-revisionid": "c19866618e0eedf062b9bf93af83b7a3750c21ee", "dirty": true, "error": null}